pydase/__init__.py
pydase/client/__init__.py
pydase/client/client.py
pydase/client/proxy_class.py
pydase/client/proxy_loader.py
pydase/components/__init__.py
pydase/components/coloured_enum.py
pydase/components/device_connection.py
pydase/components/image.py
pydase/components/number_slider.py
pydase/config.py
pydase/data_service/__init__.py
pydase/data_service/abstract_data_service.py
pydase/data_service/data_service.py
pydase/data_service/data_service_cache.py
pydase/data_service/data_service_observer.py
pydase/data_service/state_manager.py
pydase/frontend/assets/index-CKS_bS2p.js
pydase/frontend/assets/index-Cs09d5Pk.css
pydase/frontend/favicon.ico
pydase/frontend/index.html
pydase/observer_pattern/__init__.py
pydase/observer_pattern/observable/__init__.py
pydase/observer_pattern/observable/decorators.py
pydase/observer_pattern/observable/observable.py
pydase/observer_pattern/observable/observable_object.py
pydase/observer_pattern/observer/__init__.py
pydase/observer_pattern/observer/observer.py
pydase/observer_pattern/observer/property_observer.py
pydase/py.typed
pydase/server/__init__.py
pydase/server/server.py
pydase/server/web_server/__init__.py
pydase/server/web_server/api/__init__.py
pydase/server/web_server/api/v1/__init__.py
pydase/server/web_server/api/v1/application.py
pydase/server/web_server/api/v1/endpoints.py
pydase/server/web_server/sio_setup.py
pydase/server/web_server/web_server.py
pydase/task/__init__.py
pydase/task/autostart.py
pydase/task/decorator.py
pydase/task/task.py
pydase/task/task_status.py
pydase/units.py
pydase/utils/__init__.py
pydase/utils/decorators.py
pydase/utils/helpers.py
pydase/utils/logging.py
pydase/utils/serialization/__init__.py
pydase/utils/serialization/deserializer.py
pydase/utils/serialization/serializer.py
pydase/utils/serialization/types.py
pydase/version.py
pydase-0.10.21.dist-info/LICENSE
pydase-0.10.21.dist-info/METADATA
pydase-0.10.21.dist-info/WHEEL
pydase-0.10.21.dist-info/RECORD
