Metadata-Version: 2.3
Name: pydase
Version: 0.10.21
Summary: A flexible and robust Python library for creating, managing, and interacting with data services, with built-in support for web and RPC servers, and customizable features for diverse use cases.
Author: Mose Müller
Author-email: mosemueller@gmail.com
Requires-Python: >=3.10,<4.0
Classifier: Programming Language :: Python :: 3
Classifier: Programming Language :: Python :: 3.10
Classifier: Programming Language :: Python :: 3.11
Classifier: Programming Language :: Python :: 3.12
Classifier: Programming Language :: Python :: 3.13
Provides-Extra: socks
Requires-Dist: aiohttp (>=3.11.18,<4.0.0)
Requires-Dist: aiohttp-middlewares (>=2.4.0,<3.0.0)
Requires-Dist: aiohttp-socks (>=0.10.1,<0.11.0) ; extra == "socks"
Requires-Dist: anyio (>=4.9.0,<5.0.0)
Requires-Dist: click (>=8.2.0,<9.0.0)
Requires-Dist: confz (>=2.1.0,<3.0.0)
Requires-Dist: pint (>=0.24.4,<0.25.0)
Requires-Dist: python-socketio (>=5.13.0,<6.0.0)
Requires-Dist: toml (>=0.10.2,<0.11.0)
Requires-Dist: websocket-client (>=1.8.0,<2.0.0)
